tests/__init__.py
tests/test_timeoutd.py
timeoutd/__init__.py
timeoutd/_timeout.py
timeoutd/converters.py
timeoutd/exceptions.py
timeoutd/py.typed
timeoutd/timeout.py
timeoutd/wrappers.py
timeoutd-0.7.0.dist-info/METADATA
timeoutd-0.7.0.dist-info/WHEEL
timeoutd-0.7.0.dist-info/top_level.txt
timeoutd-0.7.0.dist-info/RECORD
