Metadata-Version: 2.1
Name: timeoutd
Version: 0.7.0
Summary: Simple way to add a timeout to any Python code.
Home-page: https://github.com/juhannc/timeoutd
Author: Johann Christensen
Author-email: johannchristensen@outlook.de
License: MIT
Project-URL: Source, https://github.com/juhannc/timeoutd.git
Project-URL: Tracker, https://github.com/juhannc/timeoutd/issues
Platform: any
Classifier: Development Status :: 4 - Beta
Classifier: Intended Audience :: Developers
Classifier: License :: OSI Approved :: MIT License
Classifier: Natural Language :: English
Classifier: Operating System :: OS Independent
Classifier: Programming Language :: Python :: 3 :: Only
Classifier: Programming Language :: Python :: 3.11
Classifier: Programming Language :: Python :: 3.10
Classifier: Programming Language :: Python :: 3.8
Classifier: Programming Language :: Python :: 3.9
Classifier: Topic :: Software Development :: Libraries :: Python Modules
Classifier: Typing :: Typed
Requires-Python: >=3.8
Provides-Extra: all
Requires-Dist: coverage ; extra == 'all'
Requires-Dist: flake8 ; extra == 'all'
Requires-Dist: mypy ; extra == 'all'
Requires-Dist: pycodestyle ; extra == 'all'
Requires-Dist: pytest (>=6.2.2) ; extra == 'all'
Requires-Dist: pytest-cov ; extra == 'all'
Provides-Extra: tests
Requires-Dist: coverage ; extra == 'tests'
Requires-Dist: flake8 ; extra == 'tests'
Requires-Dist: mypy ; extra == 'tests'
Requires-Dist: pycodestyle ; extra == 'tests'
Requires-Dist: pytest (>=6.2.2) ; extra == 'tests'
Requires-Dist: pytest-cov ; extra == 'tests'
